<package>
  <description brief="OMPL Rviz Viewer">

    3-D visualizer for cost-based planning algorithms implemented with the Open Motion Planning Library (OMPL). Publishes ROS messages to the RViz visualizer software using RViz markers. Displays all explored states, connecting edges and the final solution path. Great for learning and testing robotic motion planning algorithsm.

  </description>
  <author>David Coleman</author>
  <license>BSD</license>
  <review status="unreviewed" notes=""/>
  <url>http://ros.org/wiki/ompl_rviz_viewer</url>
  <depend package="roscpp"/>
  <depend package="roslib"/>
  <depend package="visualization_msgs"/>
  <depend package="ompl" />

  
</package>


